asyncio_throttled_writer/__init__.py
asyncio_throttled_writer/throttled_writer.py
asyncio_throttled_writer-0.1.2.dist-info/licenses/LICENSE
asyncio_throttled_writer-0.1.2.dist-info/METADATA
asyncio_throttled_writer-0.1.2.dist-info/WHEEL
asyncio_throttled_writer-0.1.2.dist-info/top_level.txt
asyncio_throttled_writer-0.1.2.dist-info/RECORD
